{
	"pattrstorage" : 	{
		"name" : "vsynth",
		"slots" : 		{
			"1" : 			{
				"id" : 1,
				"data" : 				{
					"vs_mixer_3::mixer3_in_1" : [  ],
					"vs_mixer_3::mixer3_in_2" : [  ],
					"vs_mixer_3::mixer3_in_3" : [  ],
					"vs_mixer_3::mixer3_master" : [  ],
					"vs_luma_key::luma_invert" : [ 1.0 ],
					"vs_luma_key::luma_smth" : [ 0.5 ],
					"vs_luma_key::luma_thrshld" : [ 0.4 ],
					"vs_frame_delay::fd_fdbck" : [ 0.4 ],
					"vs_frame_delay::fd_mix" : [ 50.0 ],
					"vs_frame_delay::fd_time" : [ 15.0 ],
					"vs_sync::sync_invert" : [ 0.0 ],
					"vs_sync::sync_pos" : [ 0.0 ],
					"vs_sync::sync_time" : [ 6.0 ],
					"vs_render::dim_x" : [ 960.0 ],
					"vs_render::dim_y" : [ 640.0 ],
					"vs_render::on_off" : [ 1.0 ],
					"vs_camera_s::cam_on_off" : [ 0.0 ],
					"vs_offset+rot::offrot_angle" : [ 0.028091 ],
					"vs_offset+rot::offrot_anglemenu" : [ 0.0 ],
					"vs_offset+rot::offrot_boundmode" : [ 2.0 ],
					"vs_offset+rot::offrot_x" : [ 0.0 ],
					"vs_offset+rot::offrot_x_range" : [ 0.0 ],
					"vs_offset+rot::offrot_y" : [ 0.0 ],
					"vs_offset+rot::offrot_y_range" : [ 0.0 ],
					"vs_offset+rot::offrot_zoom" : [ 1.0 ],
					"vs_wfg_2[2]::wfg2_fm" : [ 0.0 ],
					"vs_wfg_2[2]::wfg2_fm_range" : [ 0.0 ],
					"vs_wfg_2[2]::wfg2_freq" : [ 167.5 ],
					"vs_wfg_2[2]::wfg2_freq_range" : [ 0.0 ],
					"vs_wfg_2[2]::wfg2_pm" : [ 0.52381 ],
					"vs_wfg_2[2]::wfg2_pw" : [ 14.0 ],
					"vs_wfg_2[2]::wfg2_pwm" : [ 0.0 ],
					"vs_wfg_2[2]::wfg2_sync_dir" : [ 0 ],
					"vs_wfg_2[2]::wfg2_sync_lock" : [ 2.0 ],
					"vs_wfg_2[2]::wfg2_time" : [ 2.0 ],
					"vs_wfg_2[2]::wfg2_wf" : [ 4.0 ],
					"vs_wfg_2[1]::wfg2_fm" : [ 0.5 ],
					"vs_wfg_2[1]::wfg2_fm_range" : [ 0.0 ],
					"vs_wfg_2[1]::wfg2_freq" : [ 788.0 ],
					"vs_wfg_2[1]::wfg2_freq_range" : [ 0.0 ],
					"vs_wfg_2[1]::wfg2_pm" : [ 0.0 ],
					"vs_wfg_2[1]::wfg2_pw" : [ 50.0 ],
					"vs_wfg_2[1]::wfg2_pwm" : [ 0.0 ],
					"vs_wfg_2[1]::wfg2_sync_dir" : [ 0 ],
					"vs_wfg_2[1]::wfg2_sync_lock" : [ 0.0 ],
					"vs_wfg_2[1]::wfg2_time" : [ 2.0 ],
					"vs_wfg_2[1]::wfg2_wf" : [ 4.0 ],
					"vs_vca::vca_am" : [ 1.0 ],
					"vs_vca::vca_bias" : [ 0.5 ],
					"vs_vca[1]::vca_am" : [ 1.0 ],
					"vs_vca[1]::vca_bias" : [ 0.5 ],
					"vs_wfg_2[3]::wfg2_fm" : [ 0.017892 ],
					"vs_wfg_2[3]::wfg2_fm_range" : [ 0.0 ],
					"vs_wfg_2[3]::wfg2_freq" : [ 290.255249 ],
					"vs_wfg_2[3]::wfg2_freq_range" : [ 0.0 ],
					"vs_wfg_2[3]::wfg2_pm" : [ 0.0 ],
					"vs_wfg_2[3]::wfg2_pw" : [ 5.0 ],
					"vs_wfg_2[3]::wfg2_pwm" : [ 0.0 ],
					"vs_wfg_2[3]::wfg2_sync_dir" : [ 0 ],
					"vs_wfg_2[3]::wfg2_sync_lock" : [ 2.0 ],
					"vs_wfg_2[3]::wfg2_time" : [ 1.0 ],
					"vs_wfg_2[3]::wfg2_wf" : [ 3.0 ],
					"vs_wfg_2[4]::wfg2_fm" : [ 0.0 ],
					"vs_wfg_2[4]::wfg2_fm_range" : [ 0.0 ],
					"vs_wfg_2[4]::wfg2_freq" : [ 200.0 ],
					"vs_wfg_2[4]::wfg2_freq_range" : [ 0.0 ],
					"vs_wfg_2[4]::wfg2_pm" : [ 0.0 ],
					"vs_wfg_2[4]::wfg2_pw" : [ 50.0 ],
					"vs_wfg_2[4]::wfg2_pwm" : [ 0.0 ],
					"vs_wfg_2[4]::wfg2_sync_dir" : [ 0 ],
					"vs_wfg_2[4]::wfg2_sync_lock" : [ 0.0 ],
					"vs_wfg_2[4]::wfg2_time" : [ 2.0 ],
					"vs_wfg_2[4]::wfg2_wf" : [ 4.0 ]
				}

			}
,
			"7" : 			{
				"id" : 7,
				"data" : 				{
					"vs_mixer_3::mixer3_in_1" : [  ],
					"vs_mixer_3::mixer3_in_2" : [  ],
					"vs_mixer_3::mixer3_in_3" : [  ],
					"vs_mixer_3::mixer3_master" : [  ],
					"vs_luma_key::luma_invert" : [ 1.0 ],
					"vs_luma_key::luma_smth" : [ 0.5 ],
					"vs_luma_key::luma_thrshld" : [ 0.4 ],
					"vs_frame_delay::fd_fdbck" : [ 0.4 ],
					"vs_frame_delay::fd_mix" : [ 50.0 ],
					"vs_frame_delay::fd_time" : [ 17.0 ],
					"vs_sync::sync_invert" : [ 0.0 ],
					"vs_sync::sync_pos" : [ 0.0 ],
					"vs_sync::sync_time" : [ 6.0 ],
					"vs_render::dim_x" : [ 640.0 ],
					"vs_render::dim_y" : [ 480.0 ],
					"vs_render::on_off" : [ 1.0 ],
					"vs_camera_s::cam_on_off" : [ 1.0 ],
					"vs_offset+rot::offrot_angle" : [ 0.01377 ],
					"vs_offset+rot::offrot_anglemenu" : [ 0.0 ],
					"vs_offset+rot::offrot_boundmode" : [ 2.0 ],
					"vs_offset+rot::offrot_x" : [ 0.053543 ],
					"vs_offset+rot::offrot_x_range" : [ 0.0 ],
					"vs_offset+rot::offrot_y" : [ 0.034646 ],
					"vs_offset+rot::offrot_y_range" : [ 0.0 ],
					"vs_offset+rot::offrot_zoom" : [ 1.0 ],
					"vs_wfg_2[2]::wfg2_fm" : [ 0.5 ],
					"vs_wfg_2[2]::wfg2_fm_range" : [ 0.0 ],
					"vs_wfg_2[2]::wfg2_freq" : [ 60.0 ],
					"vs_wfg_2[2]::wfg2_freq_range" : [ 0.0 ],
					"vs_wfg_2[2]::wfg2_pm" : [ 0.0 ],
					"vs_wfg_2[2]::wfg2_pw" : [ 5.0 ],
					"vs_wfg_2[2]::wfg2_pwm" : [ 0.0 ],
					"vs_wfg_2[2]::wfg2_sync_dir" : [ 0 ],
					"vs_wfg_2[2]::wfg2_sync_lock" : [ 2.0 ],
					"vs_wfg_2[2]::wfg2_time" : [ 1.0 ],
					"vs_wfg_2[2]::wfg2_wf" : [ 0.0 ],
					"vs_wfg_2[1]::wfg2_fm" : [ 0.5 ],
					"vs_wfg_2[1]::wfg2_fm_range" : [ 0.0 ],
					"vs_wfg_2[1]::wfg2_freq" : [ 288.346466 ],
					"vs_wfg_2[1]::wfg2_freq_range" : [ 0.0 ],
					"vs_wfg_2[1]::wfg2_pm" : [ 0.0 ],
					"vs_wfg_2[1]::wfg2_pw" : [ 50.0 ],
					"vs_wfg_2[1]::wfg2_pwm" : [ 0.0 ],
					"vs_wfg_2[1]::wfg2_sync_dir" : [ 0 ],
					"vs_wfg_2[1]::wfg2_sync_lock" : [ 2.0 ],
					"vs_wfg_2[1]::wfg2_time" : [ 1.0 ],
					"vs_wfg_2[1]::wfg2_wf" : [ 4.0 ],
					"vs_vca::vca_am" : [ 0.543307 ],
					"vs_vca::vca_bias" : [ 0.665354 ],
					"vs_vca[1]::vca_am" : [ 1.0 ],
					"vs_vca[1]::vca_bias" : [ 0.720472 ],
					"vs_wfg_2[3]::wfg2_fm" : [ 0.008771 ],
					"vs_wfg_2[3]::wfg2_fm_range" : [ 0.0 ],
					"vs_wfg_2[3]::wfg2_freq" : [ 203.508255 ],
					"vs_wfg_2[3]::wfg2_freq_range" : [ 0.0 ],
					"vs_wfg_2[3]::wfg2_pm" : [ 0.0 ],
					"vs_wfg_2[3]::wfg2_pw" : [ 5.0 ],
					"vs_wfg_2[3]::wfg2_pwm" : [ 0.0 ],
					"vs_wfg_2[3]::wfg2_sync_dir" : [ 0 ],
					"vs_wfg_2[3]::wfg2_sync_lock" : [ 2.0 ],
					"vs_wfg_2[3]::wfg2_time" : [ 3.0 ],
					"vs_wfg_2[3]::wfg2_wf" : [ 4.0 ],
					"vs_wfg_2[4]::wfg2_fm" : [ 0.0 ],
					"vs_wfg_2[4]::wfg2_fm_range" : [ 0.0 ],
					"vs_wfg_2[4]::wfg2_freq" : [ 200.0 ],
					"vs_wfg_2[4]::wfg2_freq_range" : [ 0.0 ],
					"vs_wfg_2[4]::wfg2_pm" : [ 0.0 ],
					"vs_wfg_2[4]::wfg2_pw" : [ 50.0 ],
					"vs_wfg_2[4]::wfg2_pwm" : [ 0.0 ],
					"vs_wfg_2[4]::wfg2_sync_dir" : [ 0 ],
					"vs_wfg_2[4]::wfg2_sync_lock" : [ 0.0 ],
					"vs_wfg_2[4]::wfg2_time" : [ 6.0 ],
					"vs_wfg_2[4]::wfg2_wf" : [ 0.0 ]
				}

			}
,
			"12" : 			{
				"id" : 12,
				"data" : 				{
					"vs_mixer_3::mixer3_in_1" : [  ],
					"vs_mixer_3::mixer3_in_2" : [  ],
					"vs_mixer_3::mixer3_in_3" : [  ],
					"vs_mixer_3::mixer3_master" : [  ],
					"vs_luma_key::luma_invert" : [ 0.0 ],
					"vs_luma_key::luma_smth" : [ 0.0 ],
					"vs_luma_key::luma_thrshld" : [ 0.716535 ],
					"vs_frame_delay::fd_fdbck" : [ 1.0 ],
					"vs_frame_delay::fd_mix" : [ 50.0 ],
					"vs_frame_delay::fd_time" : [ 15.0 ],
					"vs_sync::sync_invert" : [ 0.0 ],
					"vs_sync::sync_pos" : [ 0.0 ],
					"vs_sync::sync_time" : [ 6.0 ],
					"vs_render::dim_x" : [ 640.0 ],
					"vs_render::dim_y" : [ 480.0 ],
					"vs_render::on_off" : [ 1.0 ],
					"vs_camera_s::cam_on_off" : [ 0.0 ],
					"vs_offset+rot::offrot_angle" : [ 0.025047 ],
					"vs_offset+rot::offrot_anglemenu" : [ 0.0 ],
					"vs_offset+rot::offrot_boundmode" : [ 2.0 ],
					"vs_offset+rot::offrot_x" : [ 0.053543 ],
					"vs_offset+rot::offrot_x_range" : [ 0.0 ],
					"vs_offset+rot::offrot_y" : [ 0.034646 ],
					"vs_offset+rot::offrot_y_range" : [ 0.0 ],
					"vs_offset+rot::offrot_zoom" : [ 1.0 ],
					"vs_wfg_2[2]::wfg2_fm" : [ 0.5 ],
					"vs_wfg_2[2]::wfg2_fm_range" : [ 0.0 ],
					"vs_wfg_2[2]::wfg2_freq" : [ 60.0 ],
					"vs_wfg_2[2]::wfg2_freq_range" : [ 0.0 ],
					"vs_wfg_2[2]::wfg2_pm" : [ 0.0 ],
					"vs_wfg_2[2]::wfg2_pw" : [ 5.0 ],
					"vs_wfg_2[2]::wfg2_pwm" : [ 0.0 ],
					"vs_wfg_2[2]::wfg2_sync_dir" : [ 0 ],
					"vs_wfg_2[2]::wfg2_sync_lock" : [ 2.0 ],
					"vs_wfg_2[2]::wfg2_time" : [ 1.0 ],
					"vs_wfg_2[2]::wfg2_wf" : [ 1.0 ],
					"vs_wfg_2[1]::wfg2_fm" : [ 0.5 ],
					"vs_wfg_2[1]::wfg2_fm_range" : [ 0.0 ],
					"vs_wfg_2[1]::wfg2_freq" : [ 288.346466 ],
					"vs_wfg_2[1]::wfg2_freq_range" : [ 0.0 ],
					"vs_wfg_2[1]::wfg2_pm" : [ 0.0 ],
					"vs_wfg_2[1]::wfg2_pw" : [ 50.0 ],
					"vs_wfg_2[1]::wfg2_pwm" : [ 0.0 ],
					"vs_wfg_2[1]::wfg2_sync_dir" : [ 0 ],
					"vs_wfg_2[1]::wfg2_sync_lock" : [ 0.0 ],
					"vs_wfg_2[1]::wfg2_time" : [ 1.0 ],
					"vs_wfg_2[1]::wfg2_wf" : [ 4.0 ],
					"vs_vca::vca_am" : [ 0.543307 ],
					"vs_vca::vca_bias" : [ 0.665354 ],
					"vs_vca[1]::vca_am" : [ 1.0 ],
					"vs_vca[1]::vca_bias" : [ 0.720472 ],
					"vs_wfg_2[3]::wfg2_fm" : [ 0.015953 ],
					"vs_wfg_2[3]::wfg2_fm_range" : [ 0.0 ],
					"vs_wfg_2[3]::wfg2_freq" : [ 257.820618 ],
					"vs_wfg_2[3]::wfg2_freq_range" : [ 0.0 ],
					"vs_wfg_2[3]::wfg2_pm" : [ 0.0 ],
					"vs_wfg_2[3]::wfg2_pw" : [ 5.0 ],
					"vs_wfg_2[3]::wfg2_pwm" : [ 0.0 ],
					"vs_wfg_2[3]::wfg2_sync_dir" : [ 0 ],
					"vs_wfg_2[3]::wfg2_sync_lock" : [ 2.0 ],
					"vs_wfg_2[3]::wfg2_time" : [ 3.0 ],
					"vs_wfg_2[3]::wfg2_wf" : [ 0.0 ],
					"vs_wfg_2[4]::wfg2_fm" : [ 0.0 ],
					"vs_wfg_2[4]::wfg2_fm_range" : [ 0.0 ],
					"vs_wfg_2[4]::wfg2_freq" : [ 200.0 ],
					"vs_wfg_2[4]::wfg2_freq_range" : [ 0.0 ],
					"vs_wfg_2[4]::wfg2_pm" : [ 0.0 ],
					"vs_wfg_2[4]::wfg2_pw" : [ 50.0 ],
					"vs_wfg_2[4]::wfg2_pwm" : [ 0.0 ],
					"vs_wfg_2[4]::wfg2_sync_dir" : [ 0 ],
					"vs_wfg_2[4]::wfg2_sync_lock" : [ 2.0 ],
					"vs_wfg_2[4]::wfg2_time" : [ 6.0 ],
					"vs_wfg_2[4]::wfg2_wf" : [ 0.0 ]
				}

			}
,
			"13" : 			{
				"id" : 13,
				"data" : 				{
					"vs_mixer_3::mixer3_in_1" : [ 1.0 ],
					"vs_mixer_3::mixer3_in_2" : [ 0.0 ],
					"vs_mixer_3::mixer3_in_3" : [ 0.0 ],
					"vs_mixer_3::mixer3_master" : [ 1.0 ],
					"vs_luma_key::luma_invert" : [ 1.0 ],
					"vs_luma_key::luma_smth" : [ 0.244094 ],
					"vs_luma_key::luma_thrshld" : [ 0.31496 ],
					"vs_frame_delay::fd_fdbck" : [ 0.771654 ],
					"vs_frame_delay::fd_mix" : [ 51.181103 ],
					"vs_frame_delay::fd_time" : [ 15.0 ],
					"vs_sync::sync_invert" : [ 0.0 ],
					"vs_sync::sync_pos" : [ 0.0 ],
					"vs_sync::sync_time" : [ 6.0 ],
					"vs_render::dim_x" : [ 640.0 ],
					"vs_render::dim_y" : [ 480.0 ],
					"vs_render::on_off" : [ 1.0 ],
					"vs_camera_s::cam_on_off" : [ 0.0 ],
					"vs_offset+rot::offrot_angle" : [ 0.027898 ],
					"vs_offset+rot::offrot_anglemenu" : [ 0.0 ],
					"vs_offset+rot::offrot_boundmode" : [ 2.0 ],
					"vs_offset+rot::offrot_x" : [ 0.0 ],
					"vs_offset+rot::offrot_x_range" : [ 0.0 ],
					"vs_offset+rot::offrot_y" : [ 0.0 ],
					"vs_offset+rot::offrot_y_range" : [ 0.0 ],
					"vs_offset+rot::offrot_zoom" : [ 1.0 ],
					"vs_wfg_2[2]::wfg2_fm" : [ 0.5 ],
					"vs_wfg_2[2]::wfg2_fm_range" : [ 0.0 ],
					"vs_wfg_2[2]::wfg2_freq" : [ 0.0 ],
					"vs_wfg_2[2]::wfg2_freq_range" : [ 0.0 ],
					"vs_wfg_2[2]::wfg2_pm" : [ 0.0 ],
					"vs_wfg_2[2]::wfg2_pw" : [ 5.0 ],
					"vs_wfg_2[2]::wfg2_pwm" : [ 0.0 ],
					"vs_wfg_2[2]::wfg2_sync_dir" : [ 0 ],
					"vs_wfg_2[2]::wfg2_sync_lock" : [ 2.0 ],
					"vs_wfg_2[2]::wfg2_time" : [ 0.0 ],
					"vs_wfg_2[2]::wfg2_wf" : [ 4.0 ],
					"vs_wfg_2[1]::wfg2_fm" : [ 0.5 ],
					"vs_wfg_2[1]::wfg2_fm_range" : [ 0.0 ],
					"vs_wfg_2[1]::wfg2_freq" : [ 60.0 ],
					"vs_wfg_2[1]::wfg2_freq_range" : [ 0.0 ],
					"vs_wfg_2[1]::wfg2_pm" : [ 0.0 ],
					"vs_wfg_2[1]::wfg2_pw" : [ 50.0 ],
					"vs_wfg_2[1]::wfg2_pwm" : [ 0.0 ],
					"vs_wfg_2[1]::wfg2_sync_dir" : [ 0 ],
					"vs_wfg_2[1]::wfg2_sync_lock" : [ 0.0 ],
					"vs_wfg_2[1]::wfg2_time" : [ 5.0 ],
					"vs_wfg_2[1]::wfg2_wf" : [ 4.0 ],
					"vs_vca::vca_am" : [ 1.0 ],
					"vs_vca::vca_bias" : [ 0.5 ],
					"vs_vca[1]::vca_am" : [ 1.0 ],
					"vs_vca[1]::vca_bias" : [ 0.5 ],
					"vs_wfg_2[3]::wfg2_fm" : [ 0.01777 ],
					"vs_wfg_2[3]::wfg2_fm_range" : [ 0.0 ],
					"vs_wfg_2[3]::wfg2_freq" : [ 700.787415 ],
					"vs_wfg_2[3]::wfg2_freq_range" : [ 0.0 ],
					"vs_wfg_2[3]::wfg2_pm" : [ 0.0 ],
					"vs_wfg_2[3]::wfg2_pw" : [ 17.321102 ],
					"vs_wfg_2[3]::wfg2_pwm" : [ 0.0 ],
					"vs_wfg_2[3]::wfg2_sync_dir" : [ 0 ],
					"vs_wfg_2[3]::wfg2_sync_lock" : [ 2.0 ],
					"vs_wfg_2[3]::wfg2_time" : [ 5.0 ],
					"vs_wfg_2[3]::wfg2_wf" : [ 4.0 ],
					"vs_wfg_2[4]::wfg2_fm" : [ 0.0 ],
					"vs_wfg_2[4]::wfg2_fm_range" : [ 0.0 ],
					"vs_wfg_2[4]::wfg2_freq" : [ 200.0 ],
					"vs_wfg_2[4]::wfg2_freq_range" : [ 0.0 ],
					"vs_wfg_2[4]::wfg2_pm" : [ 0.0 ],
					"vs_wfg_2[4]::wfg2_pw" : [ 50.0 ],
					"vs_wfg_2[4]::wfg2_pwm" : [ 0.0 ],
					"vs_wfg_2[4]::wfg2_sync_dir" : [ 0 ],
					"vs_wfg_2[4]::wfg2_sync_lock" : [ 0.0 ],
					"vs_wfg_2[4]::wfg2_time" : [ 6.0 ],
					"vs_wfg_2[4]::wfg2_wf" : [ 0.0 ]
				}

			}
,
			"14" : 			{
				"id" : 14,
				"data" : 				{
					"vs_mixer_3::mixer3_in_1" : [  ],
					"vs_mixer_3::mixer3_in_2" : [  ],
					"vs_mixer_3::mixer3_in_3" : [  ],
					"vs_mixer_3::mixer3_master" : [  ],
					"vs_luma_key::luma_invert" : [ 1.0 ],
					"vs_luma_key::luma_smth" : [ 0.5 ],
					"vs_luma_key::luma_thrshld" : [ 0.519685 ],
					"vs_frame_delay::fd_fdbck" : [ 0.4 ],
					"vs_frame_delay::fd_mix" : [ 50.0 ],
					"vs_frame_delay::fd_time" : [ 15.0 ],
					"vs_sync::sync_invert" : [ 0.0 ],
					"vs_sync::sync_pos" : [ 0.0 ],
					"vs_sync::sync_time" : [ 6.0 ],
					"vs_render::dim_x" : [ 720.0 ],
					"vs_render::dim_y" : [ 480.0 ],
					"vs_render::on_off" : [ 1.0 ],
					"vs_camera_s::cam_on_off" : [ 0.0 ],
					"vs_offset+rot::offrot_angle" : [ 0.018934 ],
					"vs_offset+rot::offrot_anglemenu" : [ 0.0 ],
					"vs_offset+rot::offrot_boundmode" : [ 2.0 ],
					"vs_offset+rot::offrot_x" : [ 0.1 ],
					"vs_offset+rot::offrot_x_range" : [ 0.0 ],
					"vs_offset+rot::offrot_y" : [ 0.0 ],
					"vs_offset+rot::offrot_y_range" : [ 0.0 ],
					"vs_offset+rot::offrot_zoom" : [ 1.0 ],
					"vs_wfg_2[2]::wfg2_fm" : [ 0.777778 ],
					"vs_wfg_2[2]::wfg2_fm_range" : [ 0.0 ],
					"vs_wfg_2[2]::wfg2_freq" : [ 0.0 ],
					"vs_wfg_2[2]::wfg2_freq_range" : [ 0.0 ],
					"vs_wfg_2[2]::wfg2_pm" : [ 3.0 ],
					"vs_wfg_2[2]::wfg2_pw" : [ 71.92244 ],
					"vs_wfg_2[2]::wfg2_pwm" : [ 0.0 ],
					"vs_wfg_2[2]::wfg2_sync_dir" : [ 0 ],
					"vs_wfg_2[2]::wfg2_sync_lock" : [ 2.0 ],
					"vs_wfg_2[2]::wfg2_time" : [ 0.0 ],
					"vs_wfg_2[2]::wfg2_wf" : [ 0.0 ],
					"vs_wfg_2[1]::wfg2_fm" : [ 0.690476 ],
					"vs_wfg_2[1]::wfg2_fm_range" : [ 0.0 ],
					"vs_wfg_2[1]::wfg2_freq" : [ 96.14286 ],
					"vs_wfg_2[1]::wfg2_freq_range" : [ 0.0 ],
					"vs_wfg_2[1]::wfg2_pm" : [ 0.0 ],
					"vs_wfg_2[1]::wfg2_pw" : [ 50.0 ],
					"vs_wfg_2[1]::wfg2_pwm" : [ 0.0 ],
					"vs_wfg_2[1]::wfg2_sync_dir" : [ 0 ],
					"vs_wfg_2[1]::wfg2_sync_lock" : [ 0.0 ],
					"vs_wfg_2[1]::wfg2_time" : [ 0.0 ],
					"vs_wfg_2[1]::wfg2_wf" : [ 4.0 ],
					"vs_vca::vca_am" : [ 1.0 ],
					"vs_vca::vca_bias" : [ 0.5 ],
					"vs_vca[1]::vca_am" : [ 1.0 ],
					"vs_vca[1]::vca_bias" : [ 0.5 ],
					"vs_wfg_2[3]::wfg2_fm" : [ 0.01206 ],
					"vs_wfg_2[3]::wfg2_fm_range" : [ 0.0 ],
					"vs_wfg_2[3]::wfg2_freq" : [ 214.959412 ],
					"vs_wfg_2[3]::wfg2_freq_range" : [ 0.0 ],
					"vs_wfg_2[3]::wfg2_pm" : [ 0.0 ],
					"vs_wfg_2[3]::wfg2_pw" : [ 66.666664 ],
					"vs_wfg_2[3]::wfg2_pwm" : [ 0.0 ],
					"vs_wfg_2[3]::wfg2_sync_dir" : [ 0 ],
					"vs_wfg_2[3]::wfg2_sync_lock" : [ 2.0 ],
					"vs_wfg_2[3]::wfg2_time" : [ 8.0 ],
					"vs_wfg_2[3]::wfg2_wf" : [ 4.0 ],
					"vs_wfg_2[4]::wfg2_fm" : [ -0.269841 ],
					"vs_wfg_2[4]::wfg2_fm_range" : [ 0.0 ],
					"vs_wfg_2[4]::wfg2_freq" : [ 651.142883 ],
					"vs_wfg_2[4]::wfg2_freq_range" : [ 0.0 ],
					"vs_wfg_2[4]::wfg2_pm" : [ 0.0 ],
					"vs_wfg_2[4]::wfg2_pw" : [ 50.0 ],
					"vs_wfg_2[4]::wfg2_pwm" : [ 0.0 ],
					"vs_wfg_2[4]::wfg2_sync_dir" : [ 0 ],
					"vs_wfg_2[4]::wfg2_sync_lock" : [ 0.0 ],
					"vs_wfg_2[4]::wfg2_time" : [ 4.0 ],
					"vs_wfg_2[4]::wfg2_wf" : [ 2.0 ]
				}

			}
,
			"29" : 			{
				"id" : 29,
				"data" : 				{
					"vs_mixer_3::mixer3_in_1" : [  ],
					"vs_mixer_3::mixer3_in_2" : [  ],
					"vs_mixer_3::mixer3_in_3" : [  ],
					"vs_mixer_3::mixer3_master" : [  ],
					"vs_luma_key::luma_invert" : [ 1.0 ],
					"vs_luma_key::luma_smth" : [ 0.5 ],
					"vs_luma_key::luma_thrshld" : [ 0.4 ],
					"vs_frame_delay::fd_fdbck" : [ 0.4 ],
					"vs_frame_delay::fd_mix" : [ 50.0 ],
					"vs_frame_delay::fd_time" : [ 17.0 ],
					"vs_sync::sync_invert" : [ 0.0 ],
					"vs_sync::sync_pos" : [ 0.0 ],
					"vs_sync::sync_time" : [ 6.0 ],
					"vs_render::dim_x" : [ 640.0 ],
					"vs_render::dim_y" : [ 480.0 ],
					"vs_render::on_off" : [ 1.0 ],
					"vs_camera_s::cam_on_off" : [ 1.0 ],
					"vs_offset+rot::offrot_angle" : [ 0.016104 ],
					"vs_offset+rot::offrot_anglemenu" : [ 0.0 ],
					"vs_offset+rot::offrot_boundmode" : [ 2.0 ],
					"vs_offset+rot::offrot_x" : [ 0.0 ],
					"vs_offset+rot::offrot_x_range" : [ 0.0 ],
					"vs_offset+rot::offrot_y" : [ 0.0 ],
					"vs_offset+rot::offrot_y_range" : [ 0.0 ],
					"vs_offset+rot::offrot_zoom" : [ 1.0 ],
					"vs_wfg_2[2]::wfg2_fm" : [ 0.5 ],
					"vs_wfg_2[2]::wfg2_fm_range" : [ 0.0 ],
					"vs_wfg_2[2]::wfg2_freq" : [ 60.0 ],
					"vs_wfg_2[2]::wfg2_freq_range" : [ 0.0 ],
					"vs_wfg_2[2]::wfg2_pm" : [ 0.0 ],
					"vs_wfg_2[2]::wfg2_pw" : [ 5.0 ],
					"vs_wfg_2[2]::wfg2_pwm" : [ 0.0 ],
					"vs_wfg_2[2]::wfg2_sync_dir" : [ 0 ],
					"vs_wfg_2[2]::wfg2_sync_lock" : [ 2.0 ],
					"vs_wfg_2[2]::wfg2_time" : [ 1.0 ],
					"vs_wfg_2[2]::wfg2_wf" : [ 3.0 ],
					"vs_wfg_2[1]::wfg2_fm" : [ 0.5 ],
					"vs_wfg_2[1]::wfg2_fm_range" : [ 0.0 ],
					"vs_wfg_2[1]::wfg2_freq" : [ 60.0 ],
					"vs_wfg_2[1]::wfg2_freq_range" : [ 0.0 ],
					"vs_wfg_2[1]::wfg2_pm" : [ 0.0 ],
					"vs_wfg_2[1]::wfg2_pw" : [ 50.0 ],
					"vs_wfg_2[1]::wfg2_pwm" : [ 0.0 ],
					"vs_wfg_2[1]::wfg2_sync_dir" : [ 0 ],
					"vs_wfg_2[1]::wfg2_sync_lock" : [ 0.0 ],
					"vs_wfg_2[1]::wfg2_time" : [ 1.0 ],
					"vs_wfg_2[1]::wfg2_wf" : [ 3.0 ],
					"vs_vca::vca_am" : [ 1.0 ],
					"vs_vca::vca_bias" : [ 0.5 ],
					"vs_vca[1]::vca_am" : [ 1.0 ],
					"vs_vca[1]::vca_bias" : [ 0.5 ],
					"vs_wfg_2[3]::wfg2_fm" : [ 0.010257 ],
					"vs_wfg_2[3]::wfg2_fm_range" : [ 0.0 ],
					"vs_wfg_2[3]::wfg2_freq" : [ 204.102905 ],
					"vs_wfg_2[3]::wfg2_freq_range" : [ 0.0 ],
					"vs_wfg_2[3]::wfg2_pm" : [ 0.0 ],
					"vs_wfg_2[3]::wfg2_pw" : [ 44.366142 ],
					"vs_wfg_2[3]::wfg2_pwm" : [ 0.0 ],
					"vs_wfg_2[3]::wfg2_sync_dir" : [ 0 ],
					"vs_wfg_2[3]::wfg2_sync_lock" : [ 2.0 ],
					"vs_wfg_2[3]::wfg2_time" : [ 1.0 ],
					"vs_wfg_2[3]::wfg2_wf" : [ 2.0 ],
					"vs_wfg_2[4]::wfg2_fm" : [ 0.0 ],
					"vs_wfg_2[4]::wfg2_fm_range" : [ 0.0 ],
					"vs_wfg_2[4]::wfg2_freq" : [ 200.0 ],
					"vs_wfg_2[4]::wfg2_freq_range" : [ 0.0 ],
					"vs_wfg_2[4]::wfg2_pm" : [ 0.0 ],
					"vs_wfg_2[4]::wfg2_pw" : [ 50.0 ],
					"vs_wfg_2[4]::wfg2_pwm" : [ 0.0 ],
					"vs_wfg_2[4]::wfg2_sync_dir" : [ 0 ],
					"vs_wfg_2[4]::wfg2_sync_lock" : [ 0.0 ],
					"vs_wfg_2[4]::wfg2_time" : [ 6.0 ],
					"vs_wfg_2[4]::wfg2_wf" : [ 2.0 ]
				}

			}
,
			"35" : 			{
				"id" : 35,
				"data" : 				{
					"vs_mixer_3::mixer3_in_1" : [  ],
					"vs_mixer_3::mixer3_in_2" : [  ],
					"vs_mixer_3::mixer3_in_3" : [  ],
					"vs_mixer_3::mixer3_master" : [  ],
					"vs_luma_key::luma_invert" : [ 0.0 ],
					"vs_luma_key::luma_smth" : [ 0.5 ],
					"vs_luma_key::luma_thrshld" : [ 0.669291 ],
					"vs_frame_delay::fd_fdbck" : [ 0.4 ],
					"vs_frame_delay::fd_mix" : [ 50.0 ],
					"vs_frame_delay::fd_time" : [ 17.0 ],
					"vs_sync::sync_invert" : [ 0.0 ],
					"vs_sync::sync_pos" : [ 0.0 ],
					"vs_sync::sync_time" : [ 6.0 ],
					"vs_render::dim_x" : [ 640.0 ],
					"vs_render::dim_y" : [ 480.0 ],
					"vs_render::on_off" : [ 1.0 ],
					"vs_camera_s::cam_on_off" : [ 1.0 ],
					"vs_offset+rot::offrot_angle" : [ 0.01402 ],
					"vs_offset+rot::offrot_anglemenu" : [ 0.0 ],
					"vs_offset+rot::offrot_boundmode" : [ 2.0 ],
					"vs_offset+rot::offrot_x" : [ 0.053543 ],
					"vs_offset+rot::offrot_x_range" : [ 0.0 ],
					"vs_offset+rot::offrot_y" : [ 0.034646 ],
					"vs_offset+rot::offrot_y_range" : [ 0.0 ],
					"vs_offset+rot::offrot_zoom" : [ 1.0 ],
					"vs_wfg_2[2]::wfg2_fm" : [ 0.5 ],
					"vs_wfg_2[2]::wfg2_fm_range" : [ 0.0 ],
					"vs_wfg_2[2]::wfg2_freq" : [ 60.0 ],
					"vs_wfg_2[2]::wfg2_freq_range" : [ 0.0 ],
					"vs_wfg_2[2]::wfg2_pm" : [ 0.0 ],
					"vs_wfg_2[2]::wfg2_pw" : [ 5.0 ],
					"vs_wfg_2[2]::wfg2_pwm" : [ 0.0 ],
					"vs_wfg_2[2]::wfg2_sync_dir" : [ 0 ],
					"vs_wfg_2[2]::wfg2_sync_lock" : [ 2.0 ],
					"vs_wfg_2[2]::wfg2_time" : [ 1.0 ],
					"vs_wfg_2[2]::wfg2_wf" : [ 0.0 ],
					"vs_wfg_2[1]::wfg2_fm" : [ 0.5 ],
					"vs_wfg_2[1]::wfg2_fm_range" : [ 0.0 ],
					"vs_wfg_2[1]::wfg2_freq" : [ 288.346466 ],
					"vs_wfg_2[1]::wfg2_freq_range" : [ 0.0 ],
					"vs_wfg_2[1]::wfg2_pm" : [ 0.0 ],
					"vs_wfg_2[1]::wfg2_pw" : [ 50.0 ],
					"vs_wfg_2[1]::wfg2_pwm" : [ 0.0 ],
					"vs_wfg_2[1]::wfg2_sync_dir" : [ 0 ],
					"vs_wfg_2[1]::wfg2_sync_lock" : [ 2.0 ],
					"vs_wfg_2[1]::wfg2_time" : [ 1.0 ],
					"vs_wfg_2[1]::wfg2_wf" : [ 4.0 ],
					"vs_vca::vca_am" : [ 0.543307 ],
					"vs_vca::vca_bias" : [ 0.665354 ],
					"vs_vca[1]::vca_am" : [ 1.0 ],
					"vs_vca[1]::vca_bias" : [ 0.720472 ],
					"vs_wfg_2[3]::wfg2_fm" : [ 0.00893 ],
					"vs_wfg_2[3]::wfg2_fm_range" : [ 0.0 ],
					"vs_wfg_2[3]::wfg2_freq" : [ 203.572006 ],
					"vs_wfg_2[3]::wfg2_freq_range" : [ 0.0 ],
					"vs_wfg_2[3]::wfg2_pm" : [ 0.0 ],
					"vs_wfg_2[3]::wfg2_pw" : [ 5.0 ],
					"vs_wfg_2[3]::wfg2_pwm" : [ 0.0 ],
					"vs_wfg_2[3]::wfg2_sync_dir" : [ 0 ],
					"vs_wfg_2[3]::wfg2_sync_lock" : [ 1.0 ],
					"vs_wfg_2[3]::wfg2_time" : [ 3.0 ],
					"vs_wfg_2[3]::wfg2_wf" : [ 3.0 ],
					"vs_wfg_2[4]::wfg2_fm" : [ 0.0 ],
					"vs_wfg_2[4]::wfg2_fm_range" : [ 0.0 ],
					"vs_wfg_2[4]::wfg2_freq" : [ 200.0 ],
					"vs_wfg_2[4]::wfg2_freq_range" : [ 0.0 ],
					"vs_wfg_2[4]::wfg2_pm" : [ 0.0 ],
					"vs_wfg_2[4]::wfg2_pw" : [ 50.0 ],
					"vs_wfg_2[4]::wfg2_pwm" : [ 0.0 ],
					"vs_wfg_2[4]::wfg2_sync_dir" : [ 0 ],
					"vs_wfg_2[4]::wfg2_sync_lock" : [ 0.0 ],
					"vs_wfg_2[4]::wfg2_time" : [ 6.0 ],
					"vs_wfg_2[4]::wfg2_wf" : [ 5.0 ]
				}

			}
,
			"36" : 			{
				"id" : 36,
				"data" : 				{
					"vs_mixer_3::mixer3_in_1" : [  ],
					"vs_mixer_3::mixer3_in_2" : [  ],
					"vs_mixer_3::mixer3_in_3" : [  ],
					"vs_mixer_3::mixer3_master" : [  ],
					"vs_luma_key::luma_invert" : [ 0.0 ],
					"vs_luma_key::luma_smth" : [ 0.5 ],
					"vs_luma_key::luma_thrshld" : [ 0.669291 ],
					"vs_frame_delay::fd_fdbck" : [ 0.787402 ],
					"vs_frame_delay::fd_mix" : [ 50.0 ],
					"vs_frame_delay::fd_time" : [ 49.0 ],
					"vs_sync::sync_invert" : [ 0.0 ],
					"vs_sync::sync_pos" : [ 0.0 ],
					"vs_sync::sync_time" : [ 6.0 ],
					"vs_render::dim_x" : [ 640.0 ],
					"vs_render::dim_y" : [ 480.0 ],
					"vs_render::on_off" : [ 1.0 ],
					"vs_camera_s::cam_on_off" : [ 1.0 ],
					"vs_offset+rot::offrot_angle" : [ 0.013895 ],
					"vs_offset+rot::offrot_anglemenu" : [ 0.0 ],
					"vs_offset+rot::offrot_boundmode" : [ 2.0 ],
					"vs_offset+rot::offrot_x" : [ 0.053543 ],
					"vs_offset+rot::offrot_x_range" : [ 0.0 ],
					"vs_offset+rot::offrot_y" : [ 0.034646 ],
					"vs_offset+rot::offrot_y_range" : [ 0.0 ],
					"vs_offset+rot::offrot_zoom" : [ 1.0 ],
					"vs_wfg_2[2]::wfg2_fm" : [ 0.5 ],
					"vs_wfg_2[2]::wfg2_fm_range" : [ 0.0 ],
					"vs_wfg_2[2]::wfg2_freq" : [ 60.0 ],
					"vs_wfg_2[2]::wfg2_freq_range" : [ 0.0 ],
					"vs_wfg_2[2]::wfg2_pm" : [ 0.0 ],
					"vs_wfg_2[2]::wfg2_pw" : [ 5.0 ],
					"vs_wfg_2[2]::wfg2_pwm" : [ 0.0 ],
					"vs_wfg_2[2]::wfg2_sync_dir" : [ 0 ],
					"vs_wfg_2[2]::wfg2_sync_lock" : [ 2.0 ],
					"vs_wfg_2[2]::wfg2_time" : [ 1.0 ],
					"vs_wfg_2[2]::wfg2_wf" : [ 0.0 ],
					"vs_wfg_2[1]::wfg2_fm" : [ 0.5 ],
					"vs_wfg_2[1]::wfg2_fm_range" : [ 0.0 ],
					"vs_wfg_2[1]::wfg2_freq" : [ 288.346466 ],
					"vs_wfg_2[1]::wfg2_freq_range" : [ 0.0 ],
					"vs_wfg_2[1]::wfg2_pm" : [ 0.0 ],
					"vs_wfg_2[1]::wfg2_pw" : [ 50.0 ],
					"vs_wfg_2[1]::wfg2_pwm" : [ 0.0 ],
					"vs_wfg_2[1]::wfg2_sync_dir" : [ 0 ],
					"vs_wfg_2[1]::wfg2_sync_lock" : [ 2.0 ],
					"vs_wfg_2[1]::wfg2_time" : [ 1.0 ],
					"vs_wfg_2[1]::wfg2_wf" : [ 4.0 ],
					"vs_vca::vca_am" : [ 0.543307 ],
					"vs_vca::vca_bias" : [ 0.665354 ],
					"vs_vca[1]::vca_am" : [ 1.0 ],
					"vs_vca[1]::vca_bias" : [ 0.720472 ],
					"vs_wfg_2[3]::wfg2_fm" : [ 0.00885 ],
					"vs_wfg_2[3]::wfg2_fm_range" : [ 0.0 ],
					"vs_wfg_2[3]::wfg2_freq" : [ 203.540131 ],
					"vs_wfg_2[3]::wfg2_freq_range" : [ 0.0 ],
					"vs_wfg_2[3]::wfg2_pm" : [ 0.0 ],
					"vs_wfg_2[3]::wfg2_pw" : [ 5.0 ],
					"vs_wfg_2[3]::wfg2_pwm" : [ 0.0 ],
					"vs_wfg_2[3]::wfg2_sync_dir" : [ 0 ],
					"vs_wfg_2[3]::wfg2_sync_lock" : [ 2.0 ],
					"vs_wfg_2[3]::wfg2_time" : [ 3.0 ],
					"vs_wfg_2[3]::wfg2_wf" : [ 0.0 ],
					"vs_wfg_2[4]::wfg2_fm" : [ 0.0 ],
					"vs_wfg_2[4]::wfg2_fm_range" : [ 0.0 ],
					"vs_wfg_2[4]::wfg2_freq" : [ 200.0 ],
					"vs_wfg_2[4]::wfg2_freq_range" : [ 0.0 ],
					"vs_wfg_2[4]::wfg2_pm" : [ 0.0 ],
					"vs_wfg_2[4]::wfg2_pw" : [ 50.0 ],
					"vs_wfg_2[4]::wfg2_pwm" : [ 0.0 ],
					"vs_wfg_2[4]::wfg2_sync_dir" : [ 0 ],
					"vs_wfg_2[4]::wfg2_sync_lock" : [ 2.0 ],
					"vs_wfg_2[4]::wfg2_time" : [ 6.0 ],
					"vs_wfg_2[4]::wfg2_wf" : [ 0.0 ]
				}

			}
,
			"43" : 			{
				"id" : 43,
				"data" : 				{
					"vs_mixer_3::mixer3_in_1" : [ 0.0 ],
					"vs_mixer_3::mixer3_in_2" : [ 0.0 ],
					"vs_mixer_3::mixer3_in_3" : [ 1.0 ],
					"vs_mixer_3::mixer3_master" : [ 1.0 ],
					"vs_luma_key::luma_invert" : [ 1.0 ],
					"vs_luma_key::luma_smth" : [ 0.244094 ],
					"vs_luma_key::luma_thrshld" : [ 0.763779 ],
					"vs_frame_delay::fd_fdbck" : [ 0.771654 ],
					"vs_frame_delay::fd_mix" : [ 51.181103 ],
					"vs_frame_delay::fd_time" : [ 25.0 ],
					"vs_sync::sync_invert" : [ 0.0 ],
					"vs_sync::sync_pos" : [ 0.0 ],
					"vs_sync::sync_time" : [ 6.0 ],
					"vs_render::dim_x" : [ 720.0 ],
					"vs_render::dim_y" : [ 480.0 ],
					"vs_render::on_off" : [ 1.0 ],
					"vs_camera_s::cam_on_off" : [ 0.0 ],
					"vs_offset+rot::offrot_angle" : [ 0.122135 ],
					"vs_offset+rot::offrot_anglemenu" : [ 0.0 ],
					"vs_offset+rot::offrot_boundmode" : [ 2.0 ],
					"vs_offset+rot::offrot_x" : [ 0.0 ],
					"vs_offset+rot::offrot_x_range" : [ 0.0 ],
					"vs_offset+rot::offrot_y" : [ 0.0 ],
					"vs_offset+rot::offrot_y_range" : [ 0.0 ],
					"vs_offset+rot::offrot_zoom" : [ 1.0 ],
					"vs_wfg_2[2]::wfg2_fm" : [ 0.0 ],
					"vs_wfg_2[2]::wfg2_fm_range" : [ 0.0 ],
					"vs_wfg_2[2]::wfg2_freq" : [ 112.0 ],
					"vs_wfg_2[2]::wfg2_freq_range" : [ 0.0 ],
					"vs_wfg_2[2]::wfg2_pm" : [ 0.047619 ],
					"vs_wfg_2[2]::wfg2_pw" : [ 3.174603 ],
					"vs_wfg_2[2]::wfg2_pwm" : [ 0.0 ],
					"vs_wfg_2[2]::wfg2_sync_dir" : [ 0 ],
					"vs_wfg_2[2]::wfg2_sync_lock" : [ 2.0 ],
					"vs_wfg_2[2]::wfg2_time" : [ 1.0 ],
					"vs_wfg_2[2]::wfg2_wf" : [ 4.0 ],
					"vs_wfg_2[1]::wfg2_fm" : [ -0.047619 ],
					"vs_wfg_2[1]::wfg2_fm_range" : [ 0.0 ],
					"vs_wfg_2[1]::wfg2_freq" : [ 64.428574 ],
					"vs_wfg_2[1]::wfg2_freq_range" : [ 0.0 ],
					"vs_wfg_2[1]::wfg2_pm" : [ 0.0 ],
					"vs_wfg_2[1]::wfg2_pw" : [ 50.0 ],
					"vs_wfg_2[1]::wfg2_pwm" : [ 0.0 ],
					"vs_wfg_2[1]::wfg2_sync_dir" : [ 0 ],
					"vs_wfg_2[1]::wfg2_sync_lock" : [ 0.0 ],
					"vs_wfg_2[1]::wfg2_time" : [ 1.0 ],
					"vs_wfg_2[1]::wfg2_wf" : [ 4.0 ],
					"vs_vca::vca_am" : [ 1.0 ],
					"vs_vca::vca_bias" : [ 0.5 ],
					"vs_vca[1]::vca_am" : [ 1.0 ],
					"vs_vca[1]::vca_bias" : [ 0.5 ],
					"vs_wfg_2[3]::wfg2_fm" : [ 0.077793 ],
					"vs_wfg_2[3]::wfg2_fm_range" : [ 0.0 ],
					"vs_wfg_2[3]::wfg2_freq" : [ 96.14286 ],
					"vs_wfg_2[3]::wfg2_freq_range" : [ 0.0 ],
					"vs_wfg_2[3]::wfg2_pm" : [ 0.0 ],
					"vs_wfg_2[3]::wfg2_pw" : [ 17.460318 ],
					"vs_wfg_2[3]::wfg2_pwm" : [ 0.0 ],
					"vs_wfg_2[3]::wfg2_sync_dir" : [ 0 ],
					"vs_wfg_2[3]::wfg2_sync_lock" : [ 2.0 ],
					"vs_wfg_2[3]::wfg2_time" : [ 1.0 ],
					"vs_wfg_2[3]::wfg2_wf" : [ 4.0 ],
					"vs_wfg_2[4]::wfg2_fm" : [ -0.015873 ],
					"vs_wfg_2[4]::wfg2_fm_range" : [ 0.0 ],
					"vs_wfg_2[4]::wfg2_freq" : [ 200.0 ],
					"vs_wfg_2[4]::wfg2_freq_range" : [ 0.0 ],
					"vs_wfg_2[4]::wfg2_pm" : [ 0.0 ],
					"vs_wfg_2[4]::wfg2_pw" : [ 50.0 ],
					"vs_wfg_2[4]::wfg2_pwm" : [ 0.0 ],
					"vs_wfg_2[4]::wfg2_sync_dir" : [ 0 ],
					"vs_wfg_2[4]::wfg2_sync_lock" : [ 0.0 ],
					"vs_wfg_2[4]::wfg2_time" : [ 6.0 ],
					"vs_wfg_2[4]::wfg2_wf" : [ 4.0 ]
				}

			}
,
			"57" : 			{
				"id" : 57,
				"data" : 				{
					"vs_mixer_3::mixer3_in_1" : [  ],
					"vs_mixer_3::mixer3_in_2" : [  ],
					"vs_mixer_3::mixer3_in_3" : [  ],
					"vs_mixer_3::mixer3_master" : [  ],
					"vs_luma_key::luma_invert" : [ 1.0 ],
					"vs_luma_key::luma_smth" : [ 0.5 ],
					"vs_luma_key::luma_thrshld" : [ 0.4 ],
					"vs_frame_delay::fd_fdbck" : [ 0.0 ],
					"vs_frame_delay::fd_mix" : [ 50.0 ],
					"vs_frame_delay::fd_time" : [ 1.0 ],
					"vs_sync::sync_invert" : [ 0.0 ],
					"vs_sync::sync_pos" : [ 0.0 ],
					"vs_sync::sync_time" : [ 6.0 ],
					"vs_render::dim_x" : [ 640.0 ],
					"vs_render::dim_y" : [ 640.0 ],
					"vs_render::on_off" : [ 1.0 ],
					"vs_camera_s::cam_on_off" : [ 1.0 ],
					"vs_offset+rot::offrot_angle" : [ 0.030296 ],
					"vs_offset+rot::offrot_anglemenu" : [ 0.0 ],
					"vs_offset+rot::offrot_boundmode" : [ 2.0 ],
					"vs_offset+rot::offrot_x" : [ 0.028346 ],
					"vs_offset+rot::offrot_x_range" : [ 0.0 ],
					"vs_offset+rot::offrot_y" : [ 0.004724 ],
					"vs_offset+rot::offrot_y_range" : [ 0.0 ],
					"vs_offset+rot::offrot_zoom" : [ 1.0 ],
					"vs_wfg_2[2]::wfg2_fm" : [ 0.5 ],
					"vs_wfg_2[2]::wfg2_fm_range" : [ 0.0 ],
					"vs_wfg_2[2]::wfg2_freq" : [ 108.0 ],
					"vs_wfg_2[2]::wfg2_freq_range" : [ 0.0 ],
					"vs_wfg_2[2]::wfg2_pm" : [ 2.06 ],
					"vs_wfg_2[2]::wfg2_pw" : [ 41.0 ],
					"vs_wfg_2[2]::wfg2_pwm" : [ 0.0 ],
					"vs_wfg_2[2]::wfg2_sync_dir" : [ 0 ],
					"vs_wfg_2[2]::wfg2_sync_lock" : [ 2.0 ],
					"vs_wfg_2[2]::wfg2_time" : [ 9.0 ],
					"vs_wfg_2[2]::wfg2_wf" : [ 3.0 ],
					"vs_wfg_2[1]::wfg2_fm" : [ 1.0 ],
					"vs_wfg_2[1]::wfg2_fm_range" : [ 0.0 ],
					"vs_wfg_2[1]::wfg2_freq" : [ 188.0 ],
					"vs_wfg_2[1]::wfg2_freq_range" : [ 0.0 ],
					"vs_wfg_2[1]::wfg2_pm" : [ 0.0 ],
					"vs_wfg_2[1]::wfg2_pw" : [ 17.6 ],
					"vs_wfg_2[1]::wfg2_pwm" : [ 0.0 ],
					"vs_wfg_2[1]::wfg2_sync_dir" : [ 0 ],
					"vs_wfg_2[1]::wfg2_sync_lock" : [ 0.0 ],
					"vs_wfg_2[1]::wfg2_time" : [ 3.0 ],
					"vs_wfg_2[1]::wfg2_wf" : [ 1.0 ],
					"vs_vca::vca_am" : [ 1.0 ],
					"vs_vca::vca_bias" : [ 0.830709 ],
					"vs_vca[1]::vca_am" : [ 1.0 ],
					"vs_vca[1]::vca_bias" : [ 0.374016 ],
					"vs_wfg_2[3]::wfg2_fm" : [ 0.019297 ],
					"vs_wfg_2[3]::wfg2_fm_range" : [ 0.0 ],
					"vs_wfg_2[3]::wfg2_freq" : [ 207.718826 ],
					"vs_wfg_2[3]::wfg2_freq_range" : [ 0.0 ],
					"vs_wfg_2[3]::wfg2_pm" : [ 0.0 ],
					"vs_wfg_2[3]::wfg2_pw" : [ 26.257715 ],
					"vs_wfg_2[3]::wfg2_pwm" : [ 0.0 ],
					"vs_wfg_2[3]::wfg2_sync_dir" : [ 0 ],
					"vs_wfg_2[3]::wfg2_sync_lock" : [ 2.0 ],
					"vs_wfg_2[3]::wfg2_time" : [ 1.0 ],
					"vs_wfg_2[3]::wfg2_wf" : [ 4.0 ],
					"vs_wfg_2[4]::wfg2_fm" : [ 0.0 ],
					"vs_wfg_2[4]::wfg2_fm_range" : [ 0.0 ],
					"vs_wfg_2[4]::wfg2_freq" : [ 200.0 ],
					"vs_wfg_2[4]::wfg2_freq_range" : [ 0.0 ],
					"vs_wfg_2[4]::wfg2_pm" : [ 0.0 ],
					"vs_wfg_2[4]::wfg2_pw" : [ 50.0 ],
					"vs_wfg_2[4]::wfg2_pwm" : [ 0.0 ],
					"vs_wfg_2[4]::wfg2_sync_dir" : [ 0 ],
					"vs_wfg_2[4]::wfg2_sync_lock" : [ 0.0 ],
					"vs_wfg_2[4]::wfg2_time" : [ 6.0 ],
					"vs_wfg_2[4]::wfg2_wf" : [ 0.0 ]
				}

			}
,
			"58" : 			{
				"id" : 58,
				"data" : 				{
					"vs_mixer_3::mixer3_in_1" : [  ],
					"vs_mixer_3::mixer3_in_2" : [  ],
					"vs_mixer_3::mixer3_in_3" : [  ],
					"vs_mixer_3::mixer3_master" : [  ],
					"vs_luma_key::luma_invert" : [ 1.0 ],
					"vs_luma_key::luma_smth" : [ 0.5 ],
					"vs_luma_key::luma_thrshld" : [ 0.4 ],
					"vs_frame_delay::fd_fdbck" : [ 0.4 ],
					"vs_frame_delay::fd_mix" : [ 50.0 ],
					"vs_frame_delay::fd_time" : [ 17.0 ],
					"vs_sync::sync_invert" : [ 0.0 ],
					"vs_sync::sync_pos" : [ 0.0 ],
					"vs_sync::sync_time" : [ 6.0 ],
					"vs_render::dim_x" : [ 640.0 ],
					"vs_render::dim_y" : [ 480.0 ],
					"vs_render::on_off" : [ 1.0 ],
					"vs_camera_s::cam_on_off" : [ 1.0 ],
					"vs_offset+rot::offrot_angle" : [ 0.147852 ],
					"vs_offset+rot::offrot_anglemenu" : [ 0.0 ],
					"vs_offset+rot::offrot_boundmode" : [ 2.0 ],
					"vs_offset+rot::offrot_x" : [ 0.053543 ],
					"vs_offset+rot::offrot_x_range" : [ 0.0 ],
					"vs_offset+rot::offrot_y" : [ 0.034646 ],
					"vs_offset+rot::offrot_y_range" : [ 0.0 ],
					"vs_offset+rot::offrot_zoom" : [ 1.0 ],
					"vs_wfg_2[2]::wfg2_fm" : [ 0.5 ],
					"vs_wfg_2[2]::wfg2_fm_range" : [ 0.0 ],
					"vs_wfg_2[2]::wfg2_freq" : [ 60.0 ],
					"vs_wfg_2[2]::wfg2_freq_range" : [ 0.0 ],
					"vs_wfg_2[2]::wfg2_pm" : [ 0.0 ],
					"vs_wfg_2[2]::wfg2_pw" : [ 28.619684 ],
					"vs_wfg_2[2]::wfg2_pwm" : [ 0.0 ],
					"vs_wfg_2[2]::wfg2_sync_dir" : [ 0 ],
					"vs_wfg_2[2]::wfg2_sync_lock" : [ 2.0 ],
					"vs_wfg_2[2]::wfg2_time" : [ 7.0 ],
					"vs_wfg_2[2]::wfg2_wf" : [ 0.0 ],
					"vs_wfg_2[1]::wfg2_fm" : [ 0.5 ],
					"vs_wfg_2[1]::wfg2_fm_range" : [ 0.0 ],
					"vs_wfg_2[1]::wfg2_freq" : [ 288.346466 ],
					"vs_wfg_2[1]::wfg2_freq_range" : [ 0.0 ],
					"vs_wfg_2[1]::wfg2_pm" : [ 0.0 ],
					"vs_wfg_2[1]::wfg2_pw" : [ 50.0 ],
					"vs_wfg_2[1]::wfg2_pwm" : [ 0.0 ],
					"vs_wfg_2[1]::wfg2_sync_dir" : [ 0 ],
					"vs_wfg_2[1]::wfg2_sync_lock" : [ 2.0 ],
					"vs_wfg_2[1]::wfg2_time" : [ 5.0 ],
					"vs_wfg_2[1]::wfg2_wf" : [ 4.0 ],
					"vs_vca::vca_am" : [ 0.543307 ],
					"vs_vca::vca_bias" : [ 0.665354 ],
					"vs_vca[1]::vca_am" : [ 1.0 ],
					"vs_vca[1]::vca_bias" : [ 0.720472 ],
					"vs_wfg_2[3]::wfg2_fm" : [ 0.094173 ],
					"vs_wfg_2[3]::wfg2_fm_range" : [ 0.0 ],
					"vs_wfg_2[3]::wfg2_freq" : [ 237.669296 ],
					"vs_wfg_2[3]::wfg2_freq_range" : [ 0.0 ],
					"vs_wfg_2[3]::wfg2_pm" : [ 0.0 ],
					"vs_wfg_2[3]::wfg2_pw" : [ 44.366142 ],
					"vs_wfg_2[3]::wfg2_pwm" : [ 0.0 ],
					"vs_wfg_2[3]::wfg2_sync_dir" : [ 0 ],
					"vs_wfg_2[3]::wfg2_sync_lock" : [ 2.0 ],
					"vs_wfg_2[3]::wfg2_time" : [ 7.0 ],
					"vs_wfg_2[3]::wfg2_wf" : [ 4.0 ],
					"vs_wfg_2[4]::wfg2_fm" : [ 0.0 ],
					"vs_wfg_2[4]::wfg2_fm_range" : [ 0.0 ],
					"vs_wfg_2[4]::wfg2_freq" : [ 420.472443 ],
					"vs_wfg_2[4]::wfg2_freq_range" : [ 0.0 ],
					"vs_wfg_2[4]::wfg2_pm" : [ 0.0 ],
					"vs_wfg_2[4]::wfg2_pw" : [ 50.0 ],
					"vs_wfg_2[4]::wfg2_pwm" : [ 0.0 ],
					"vs_wfg_2[4]::wfg2_sync_dir" : [ 0 ],
					"vs_wfg_2[4]::wfg2_sync_lock" : [ 0.0 ],
					"vs_wfg_2[4]::wfg2_time" : [ 6.0 ],
					"vs_wfg_2[4]::wfg2_wf" : [ 4.0 ]
				}

			}
,
			"64" : 			{
				"id" : 64,
				"data" : 				{
					"vs_mixer_3::mixer3_in_1" : [  ],
					"vs_mixer_3::mixer3_in_2" : [  ],
					"vs_mixer_3::mixer3_in_3" : [  ],
					"vs_mixer_3::mixer3_master" : [  ],
					"vs_luma_key::luma_invert" : [ 1.0 ],
					"vs_luma_key::luma_smth" : [ 0.5 ],
					"vs_luma_key::luma_thrshld" : [ 0.4 ],
					"vs_frame_delay::fd_fdbck" : [ 0.4 ],
					"vs_frame_delay::fd_mix" : [ 50.0 ],
					"vs_frame_delay::fd_time" : [ 17.0 ],
					"vs_sync::sync_invert" : [ 0.0 ],
					"vs_sync::sync_pos" : [ 0.0 ],
					"vs_sync::sync_time" : [ 6.0 ],
					"vs_render::dim_x" : [ 640.0 ],
					"vs_render::dim_y" : [ 640.0 ],
					"vs_render::on_off" : [ 1.0 ],
					"vs_camera_s::cam_on_off" : [ 1.0 ],
					"vs_offset+rot::offrot_angle" : [ 0.033275 ],
					"vs_offset+rot::offrot_anglemenu" : [ 0.0 ],
					"vs_offset+rot::offrot_boundmode" : [ 2.0 ],
					"vs_offset+rot::offrot_x" : [ 0.1 ],
					"vs_offset+rot::offrot_x_range" : [ 0.0 ],
					"vs_offset+rot::offrot_y" : [ 0.0 ],
					"vs_offset+rot::offrot_y_range" : [ 0.0 ],
					"vs_offset+rot::offrot_zoom" : [ 1.0 ],
					"vs_wfg_2[2]::wfg2_fm" : [ 0.777778 ],
					"vs_wfg_2[2]::wfg2_fm_range" : [ 0.0 ],
					"vs_wfg_2[2]::wfg2_freq" : [ 429.142853 ],
					"vs_wfg_2[2]::wfg2_freq_range" : [ 0.0 ],
					"vs_wfg_2[2]::wfg2_pm" : [ 3.0 ],
					"vs_wfg_2[2]::wfg2_pw" : [ 71.92244 ],
					"vs_wfg_2[2]::wfg2_pwm" : [ 0.0 ],
					"vs_wfg_2[2]::wfg2_sync_dir" : [ 0 ],
					"vs_wfg_2[2]::wfg2_sync_lock" : [ 2.0 ],
					"vs_wfg_2[2]::wfg2_time" : [ 7.0 ],
					"vs_wfg_2[2]::wfg2_wf" : [ 2.0 ],
					"vs_wfg_2[1]::wfg2_fm" : [ 0.690476 ],
					"vs_wfg_2[1]::wfg2_fm_range" : [ 0.0 ],
					"vs_wfg_2[1]::wfg2_freq" : [ 96.14286 ],
					"vs_wfg_2[1]::wfg2_freq_range" : [ 0.0 ],
					"vs_wfg_2[1]::wfg2_pm" : [ 0.0 ],
					"vs_wfg_2[1]::wfg2_pw" : [ 50.0 ],
					"vs_wfg_2[1]::wfg2_pwm" : [ 0.0 ],
					"vs_wfg_2[1]::wfg2_sync_dir" : [ 0 ],
					"vs_wfg_2[1]::wfg2_sync_lock" : [ 0.0 ],
					"vs_wfg_2[1]::wfg2_time" : [ 4.0 ],
					"vs_wfg_2[1]::wfg2_wf" : [ 0.0 ],
					"vs_vca::vca_am" : [ 1.0 ],
					"vs_vca::vca_bias" : [ 0.5 ],
					"vs_vca[1]::vca_am" : [ 1.0 ],
					"vs_vca[1]::vca_bias" : [ 0.5 ],
					"vs_wfg_2[3]::wfg2_fm" : [ 0.021195 ],
					"vs_wfg_2[3]::wfg2_fm_range" : [ 0.0 ],
					"vs_wfg_2[3]::wfg2_freq" : [ 208.477814 ],
					"vs_wfg_2[3]::wfg2_freq_range" : [ 0.0 ],
					"vs_wfg_2[3]::wfg2_pm" : [ 0.0 ],
					"vs_wfg_2[3]::wfg2_pw" : [ 5.0 ],
					"vs_wfg_2[3]::wfg2_pwm" : [ 0.0 ],
					"vs_wfg_2[3]::wfg2_sync_dir" : [ 0 ],
					"vs_wfg_2[3]::wfg2_sync_lock" : [ 2.0 ],
					"vs_wfg_2[3]::wfg2_time" : [ 1.0 ],
					"vs_wfg_2[3]::wfg2_wf" : [ 4.0 ],
					"vs_wfg_2[4]::wfg2_fm" : [ -0.111111 ],
					"vs_wfg_2[4]::wfg2_fm_range" : [ 0.0 ],
					"vs_wfg_2[4]::wfg2_freq" : [ 104.071426 ],
					"vs_wfg_2[4]::wfg2_freq_range" : [ 0.0 ],
					"vs_wfg_2[4]::wfg2_pm" : [ 0.0 ],
					"vs_wfg_2[4]::wfg2_pw" : [ 50.0 ],
					"vs_wfg_2[4]::wfg2_pwm" : [ 0.0 ],
					"vs_wfg_2[4]::wfg2_sync_dir" : [ 0 ],
					"vs_wfg_2[4]::wfg2_sync_lock" : [ 0.0 ],
					"vs_wfg_2[4]::wfg2_time" : [ 3.0 ],
					"vs_wfg_2[4]::wfg2_wf" : [ 2.0 ]
				}

			}
,
			"68" : 			{
				"id" : 68,
				"data" : 				{
					"vs_mixer_3::mixer3_in_1" : [  ],
					"vs_mixer_3::mixer3_in_2" : [  ],
					"vs_mixer_3::mixer3_in_3" : [  ],
					"vs_mixer_3::mixer3_master" : [  ],
					"vs_luma_key::luma_invert" : [ 1.0 ],
					"vs_luma_key::luma_smth" : [ 0.5 ],
					"vs_luma_key::luma_thrshld" : [ 0.4 ],
					"vs_frame_delay::fd_fdbck" : [ 0.4 ],
					"vs_frame_delay::fd_mix" : [ 50.0 ],
					"vs_frame_delay::fd_time" : [ 45.0 ],
					"vs_sync::sync_invert" : [ 0.0 ],
					"vs_sync::sync_pos" : [ 0.0 ],
					"vs_sync::sync_time" : [ 6.0 ],
					"vs_render::dim_x" : [ 640.0 ],
					"vs_render::dim_y" : [ 640.0 ],
					"vs_render::on_off" : [ 1.0 ],
					"vs_camera_s::cam_on_off" : [ 1.0 ],
					"vs_offset+rot::offrot_angle" : [ 0.11373 ],
					"vs_offset+rot::offrot_anglemenu" : [ 0.0 ],
					"vs_offset+rot::offrot_boundmode" : [ 2.0 ],
					"vs_offset+rot::offrot_x" : [ 0.1 ],
					"vs_offset+rot::offrot_x_range" : [ 0.0 ],
					"vs_offset+rot::offrot_y" : [ 0.0 ],
					"vs_offset+rot::offrot_y_range" : [ 0.0 ],
					"vs_offset+rot::offrot_zoom" : [ 1.0 ],
					"vs_wfg_2[2]::wfg2_fm" : [ 0.777778 ],
					"vs_wfg_2[2]::wfg2_fm_range" : [ 0.0 ],
					"vs_wfg_2[2]::wfg2_freq" : [ 238.857147 ],
					"vs_wfg_2[2]::wfg2_freq_range" : [ 0.0 ],
					"vs_wfg_2[2]::wfg2_pm" : [ 3.0 ],
					"vs_wfg_2[2]::wfg2_pw" : [ 71.92244 ],
					"vs_wfg_2[2]::wfg2_pwm" : [ 0.0 ],
					"vs_wfg_2[2]::wfg2_sync_dir" : [ 0 ],
					"vs_wfg_2[2]::wfg2_sync_lock" : [ 2.0 ],
					"vs_wfg_2[2]::wfg2_time" : [ 7.0 ],
					"vs_wfg_2[2]::wfg2_wf" : [ 0.0 ],
					"vs_wfg_2[1]::wfg2_fm" : [ 0.690476 ],
					"vs_wfg_2[1]::wfg2_fm_range" : [ 0.0 ],
					"vs_wfg_2[1]::wfg2_freq" : [ 96.14286 ],
					"vs_wfg_2[1]::wfg2_freq_range" : [ 0.0 ],
					"vs_wfg_2[1]::wfg2_pm" : [ 0.0 ],
					"vs_wfg_2[1]::wfg2_pw" : [ 50.0 ],
					"vs_wfg_2[1]::wfg2_pwm" : [ 0.0 ],
					"vs_wfg_2[1]::wfg2_sync_dir" : [ 0 ],
					"vs_wfg_2[1]::wfg2_sync_lock" : [ 0.0 ],
					"vs_wfg_2[1]::wfg2_time" : [ 4.0 ],
					"vs_wfg_2[1]::wfg2_wf" : [ 4.0 ],
					"vs_vca::vca_am" : [ 1.0 ],
					"vs_vca::vca_bias" : [ 0.5 ],
					"vs_vca[1]::vca_am" : [ 1.0 ],
					"vs_vca[1]::vca_bias" : [ 0.5 ],
					"vs_wfg_2[3]::wfg2_fm" : [ 0.07244 ],
					"vs_wfg_2[3]::wfg2_fm_range" : [ 0.0 ],
					"vs_wfg_2[3]::wfg2_freq" : [ 228.97583 ],
					"vs_wfg_2[3]::wfg2_freq_range" : [ 0.0 ],
					"vs_wfg_2[3]::wfg2_pm" : [ 0.0 ],
					"vs_wfg_2[3]::wfg2_pw" : [ 66.666664 ],
					"vs_wfg_2[3]::wfg2_pwm" : [ 0.0 ],
					"vs_wfg_2[3]::wfg2_sync_dir" : [ 0 ],
					"vs_wfg_2[3]::wfg2_sync_lock" : [ 2.0 ],
					"vs_wfg_2[3]::wfg2_time" : [ 8.0 ],
					"vs_wfg_2[3]::wfg2_wf" : [ 4.0 ],
					"vs_wfg_2[4]::wfg2_fm" : [ -0.269841 ],
					"vs_wfg_2[4]::wfg2_fm_range" : [ 0.0 ],
					"vs_wfg_2[4]::wfg2_freq" : [ 651.142883 ],
					"vs_wfg_2[4]::wfg2_freq_range" : [ 0.0 ],
					"vs_wfg_2[4]::wfg2_pm" : [ 0.0 ],
					"vs_wfg_2[4]::wfg2_pw" : [ 50.0 ],
					"vs_wfg_2[4]::wfg2_pwm" : [ 0.0 ],
					"vs_wfg_2[4]::wfg2_sync_dir" : [ 0 ],
					"vs_wfg_2[4]::wfg2_sync_lock" : [ 0.0 ],
					"vs_wfg_2[4]::wfg2_time" : [ 4.0 ],
					"vs_wfg_2[4]::wfg2_wf" : [ 2.0 ]
				}

			}
,
			"70" : 			{
				"id" : 70,
				"data" : 				{
					"vs_mixer_3::mixer3_in_1" : [ 0.088273 ],
					"vs_mixer_3::mixer3_in_2" : [ 0.0 ],
					"vs_mixer_3::mixer3_in_3" : [ 1.0 ],
					"vs_mixer_3::mixer3_master" : [ 1.0 ],
					"vs_luma_key::luma_invert" : [ 1.0 ],
					"vs_luma_key::luma_smth" : [ 0.25 ],
					"vs_luma_key::luma_thrshld" : [ 0.3 ],
					"vs_frame_delay::fd_fdbck" : [ 0.425197 ],
					"vs_frame_delay::fd_mix" : [ 71.653542 ],
					"vs_frame_delay::fd_time" : [ 46.0 ],
					"vs_sync::sync_invert" : [ 0.0 ],
					"vs_sync::sync_pos" : [ 0.0 ],
					"vs_sync::sync_time" : [ 6.0 ],
					"vs_render::dim_x" : [ 640.0 ],
					"vs_render::dim_y" : [ 480.0 ],
					"vs_render::on_off" : [ 1.0 ],
					"vs_camera_s::cam_on_off" : [ 0.0 ],
					"vs_offset+rot::offrot_angle" : [ 0.025078 ],
					"vs_offset+rot::offrot_anglemenu" : [ 0.0 ],
					"vs_offset+rot::offrot_boundmode" : [ 2.0 ],
					"vs_offset+rot::offrot_x" : [ 0.0 ],
					"vs_offset+rot::offrot_x_range" : [ 0.0 ],
					"vs_offset+rot::offrot_y" : [ 0.0 ],
					"vs_offset+rot::offrot_y_range" : [ 0.0 ],
					"vs_offset+rot::offrot_zoom" : [ 1.0 ],
					"vs_wfg_2[2]::wfg2_fm" : [ 0.19685 ],
					"vs_wfg_2[2]::wfg2_fm_range" : [ 0.0 ],
					"vs_wfg_2[2]::wfg2_freq" : [ 118.110237 ],
					"vs_wfg_2[2]::wfg2_freq_range" : [ 0.0 ],
					"vs_wfg_2[2]::wfg2_pm" : [ 2.622047 ],
					"vs_wfg_2[2]::wfg2_pw" : [ 29.130945 ],
					"vs_wfg_2[2]::wfg2_pwm" : [ 0.0 ],
					"vs_wfg_2[2]::wfg2_sync_dir" : [ 0 ],
					"vs_wfg_2[2]::wfg2_sync_lock" : [ 2.0 ],
					"vs_wfg_2[2]::wfg2_time" : [ 0.0 ],
					"vs_wfg_2[2]::wfg2_wf" : [ 0.0 ],
					"vs_wfg_2[1]::wfg2_fm" : [ 1.0 ],
					"vs_wfg_2[1]::wfg2_fm_range" : [ 0.0 ],
					"vs_wfg_2[1]::wfg2_freq" : [ 60.0 ],
					"vs_wfg_2[1]::wfg2_freq_range" : [ 0.0 ],
					"vs_wfg_2[1]::wfg2_pm" : [ 0.0 ],
					"vs_wfg_2[1]::wfg2_pw" : [ 56.687244 ],
					"vs_wfg_2[1]::wfg2_pwm" : [ 0.0 ],
					"vs_wfg_2[1]::wfg2_sync_dir" : [ 0 ],
					"vs_wfg_2[1]::wfg2_sync_lock" : [ 0.0 ],
					"vs_wfg_2[1]::wfg2_time" : [ 0.0 ],
					"vs_wfg_2[1]::wfg2_wf" : [ 0.0 ],
					"vs_vca::vca_am" : [ 0.716535 ],
					"vs_vca::vca_bias" : [ 0.633858 ],
					"vs_vca[1]::vca_am" : [ 1.0 ],
					"vs_vca[1]::vca_bias" : [ 0.858268 ],
					"vs_wfg_2[3]::wfg2_fm" : [ 0.015973 ],
					"vs_wfg_2[3]::wfg2_fm_range" : [ 0.0 ],
					"vs_wfg_2[3]::wfg2_freq" : [ 700.787415 ],
					"vs_wfg_2[3]::wfg2_freq_range" : [ 0.0 ],
					"vs_wfg_2[3]::wfg2_pm" : [ 0.0 ],
					"vs_wfg_2[3]::wfg2_pw" : [ 17.321102 ],
					"vs_wfg_2[3]::wfg2_pwm" : [ 0.0 ],
					"vs_wfg_2[3]::wfg2_sync_dir" : [ 0 ],
					"vs_wfg_2[3]::wfg2_sync_lock" : [ 2.0 ],
					"vs_wfg_2[3]::wfg2_time" : [ 6.0 ],
					"vs_wfg_2[3]::wfg2_wf" : [ 2.0 ],
					"vs_wfg_2[4]::wfg2_fm" : [ 0.0 ],
					"vs_wfg_2[4]::wfg2_fm_range" : [ 0.0 ],
					"vs_wfg_2[4]::wfg2_freq" : [ 200.0 ],
					"vs_wfg_2[4]::wfg2_freq_range" : [ 0.0 ],
					"vs_wfg_2[4]::wfg2_pm" : [ 0.0 ],
					"vs_wfg_2[4]::wfg2_pw" : [ 50.0 ],
					"vs_wfg_2[4]::wfg2_pwm" : [ 0.0 ],
					"vs_wfg_2[4]::wfg2_sync_dir" : [ 0 ],
					"vs_wfg_2[4]::wfg2_sync_lock" : [ 0.0 ],
					"vs_wfg_2[4]::wfg2_time" : [ 6.0 ],
					"vs_wfg_2[4]::wfg2_wf" : [ 2.0 ]
				}

			}

		}

	}

}
